{"acct_num": "41741", "by_industry": [{"industry": "Political / Lobbying", "total": 104186.9}, {"industry": "Other", "total": 44629.65}, {"industry": "Not Employed", "total": 43330.98}, {"industry": "Business & Consulting", "total": 32875.0}, {"industry": "Healthcare", "total": 32725.0}, {"industry": "Finance & Insurance", "total": 32075.0}, {"industry": "Retail & Hospitality", "total": 21683.73}, {"industry": "Real Estate", "total": 20575.0}, {"industry": "Legal", "total": 17500.0}, {"industry": "Retired", "total": 10413.86}, {"industry": "Agriculture", "total": 9800.0}, {"industry": "Education", "total": 8925.0}, {"industry": "Construction", "total": 4000.0}, {"industry": "Technology / Engineering", "total": 3700.0}, {"industry": "Government & Public Service", "total": 1125.0}]}