{"acct_num": "45026", "by_industry": [{"industry": "Not Employed", "total": 110898.59}, {"industry": "Other", "total": 45190.39}, {"industry": "Agriculture", "total": 25100.0}, {"industry": "Business & Consulting", "total": 21931.3}, {"industry": "Healthcare", "total": 15896.91}, {"industry": "Finance & Insurance", "total": 11475.0}, {"industry": "Legal", "total": 10775.0}, {"industry": "Real Estate", "total": 4325.0}, {"industry": "Political / Lobbying", "total": 4305.15}, {"industry": "Technology / Engineering", "total": 4000.0}, {"industry": "Construction", "total": 3050.0}, {"industry": "Education", "total": 2500.0}, {"industry": "Government & Public Service", "total": 1905.0}, {"industry": "Retail & Hospitality", "total": 1840.0}, {"industry": "Retired", "total": 1105.0}]}