{"acct_num": "45148", "by_industry": [{"industry": "Business & Consulting", "total": 25416.0}, {"industry": "Other", "total": 12161.0}, {"industry": "Real Estate", "total": 9550.0}, {"industry": "Construction", "total": 7960.0}, {"industry": "Healthcare", "total": 6785.0}, {"industry": "Political / Lobbying", "total": 5350.0}, {"industry": "Retired", "total": 3306.0}, {"industry": "Technology / Engineering", "total": 3025.0}, {"industry": "Legal", "total": 2450.0}, {"industry": "Retail & Hospitality", "total": 1000.0}, {"industry": "Finance & Insurance", "total": 808.0}, {"industry": "Education", "total": 775.0}, {"industry": "Not Employed", "total": 282.0}]}