{"acct_num": "45421", "by_industry": [{"industry": "Business & Consulting", "total": 67577.95}, {"industry": "Other", "total": 51255.88}, {"industry": "Political / Lobbying", "total": 50610.0}, {"industry": "Finance & Insurance", "total": 24250.0}, {"industry": "Healthcare", "total": 18800.0}, {"industry": "Agriculture", "total": 16475.0}, {"industry": "Construction", "total": 12050.0}, {"industry": "Not Employed", "total": 11509.1}, {"industry": "Legal", "total": 10750.0}, {"industry": "Real Estate", "total": 10500.0}, {"industry": "Retail & Hospitality", "total": 7125.0}, {"industry": "Technology / Engineering", "total": 6250.0}, {"industry": "Education", "total": 5850.0}, {"industry": "Retired", "total": 4725.0}, {"industry": "Government & Public Service", "total": 3400.0}]}