{"acct_num": "45696", "by_industry": [{"industry": "Political / Lobbying", "total": 116655.46}, {"industry": "Other", "total": 92213.8}, {"industry": "Agriculture", "total": 35693.45}, {"industry": "Business & Consulting", "total": 31500.0}, {"industry": "Not Employed", "total": 18315.0}, {"industry": "Legal", "total": 13750.0}, {"industry": "Finance & Insurance", "total": 12350.0}, {"industry": "Healthcare", "total": 8980.0}, {"industry": "Real Estate", "total": 8450.0}, {"industry": "Construction", "total": 6150.0}, {"industry": "Retail & Hospitality", "total": 5250.0}, {"industry": "Technology / Engineering", "total": 3800.0}, {"industry": "Retired", "total": 3507.5}, {"industry": "Education", "total": 2450.0}, {"industry": "Government & Public Service", "total": 750.0}]}