{"acct_num": "45866", "by_industry": [{"industry": "Other", "total": 101655.0}, {"industry": "Political / Lobbying", "total": 75095.52}, {"industry": "Agriculture", "total": 6880.0}, {"industry": "Finance & Insurance", "total": 6675.0}, {"industry": "Business & Consulting", "total": 6300.0}, {"industry": "Retired", "total": 6220.74}, {"industry": "Healthcare", "total": 6075.0}, {"industry": "Legal", "total": 6000.0}, {"industry": "Construction", "total": 4750.0}, {"industry": "Not Employed", "total": 4325.0}, {"industry": "Retail & Hospitality", "total": 3980.0}, {"industry": "Technology / Engineering", "total": 2950.0}, {"industry": "Real Estate", "total": 2475.0}, {"industry": "Government & Public Service", "total": 925.0}, {"industry": "Education", "total": 200.0}]}