{"acct_num": "45943", "by_industry": [{"industry": "Other", "total": 7210.0}, {"industry": "Legal", "total": 2910.0}, {"industry": "Not Employed", "total": 2603.0}, {"industry": "Healthcare", "total": 605.0}, {"industry": "Retired", "total": 375.0}, {"industry": "Government & Public Service", "total": 210.0}, {"industry": "Business & Consulting", "total": 195.0}, {"industry": "Education", "total": 50.0}, {"industry": "Finance & Insurance", "total": 50.0}, {"industry": "Technology / Engineering", "total": 25.0}, {"industry": "Real Estate", "total": 20.0}]}