{"acct_num": "50430", "by_industry": [{"industry": "Legal", "total": 41456.37}, {"industry": "Not Employed", "total": 24243.78}, {"industry": "Other", "total": 20331.64}, {"industry": "Business & Consulting", "total": 12757.0}, {"industry": "Political / Lobbying", "total": 9500.0}, {"industry": "Healthcare", "total": 5550.2}, {"industry": "Education", "total": 3775.0}, {"industry": "Finance & Insurance", "total": 3770.0}, {"industry": "Retired", "total": 3195.52}, {"industry": "Retail & Hospitality", "total": 2211.35}, {"industry": "Government & Public Service", "total": 1935.0}, {"industry": "Construction", "total": 1500.0}, {"industry": "Real Estate", "total": 1440.1}, {"industry": "Technology / Engineering", "total": 575.0}, {"industry": "Agriculture", "total": 500.0}]}