{"acct_num": "50442", "by_industry": [{"industry": "Finance & Insurance", "total": 82100.0}, {"industry": "Other", "total": 49371.3}, {"industry": "Political / Lobbying", "total": 49073.78}, {"industry": "Business & Consulting", "total": 25564.41}, {"industry": "Healthcare", "total": 21960.0}, {"industry": "Real Estate", "total": 13850.0}, {"industry": "Legal", "total": 9750.0}, {"industry": "Not Employed", "total": 9485.0}, {"industry": "Retail & Hospitality", "total": 6890.0}, {"industry": "Retired", "total": 6360.0}, {"industry": "Construction", "total": 4850.0}, {"industry": "Education", "total": 4095.0}, {"industry": "Government & Public Service", "total": 1200.0}, {"industry": "Technology / Engineering", "total": 1200.0}, {"industry": "Agriculture", "total": 1050.0}]}