{"acct_num": "50764", "by_industry": [{"industry": "Business & Consulting", "total": 232042.99}, {"industry": "Political / Lobbying", "total": 147955.99}, {"industry": "Other", "total": 140764.71}, {"industry": "Healthcare", "total": 119236.59}, {"industry": "Legal", "total": 53430.0}, {"industry": "Agriculture", "total": 47616.0}, {"industry": "Finance & Insurance", "total": 43430.0}, {"industry": "Not Employed", "total": 37845.99}, {"industry": "Real Estate", "total": 36798.43}, {"industry": "Education", "total": 21383.12}, {"industry": "Retired", "total": 20363.12}, {"industry": "Retail & Hospitality", "total": 17650.0}, {"industry": "Construction", "total": 13100.0}, {"industry": "Technology / Engineering", "total": 12840.0}, {"industry": "Government & Public Service", "total": 3727.0}]}