{"acct_num": "55152", "by_industry": [{"industry": "Legal", "total": 88777.55}, {"industry": "Other", "total": 8294.28}, {"industry": "Business & Consulting", "total": 7480.0}, {"industry": "Retired", "total": 3770.0}, {"industry": "Real Estate", "total": 3400.0}, {"industry": "Education", "total": 2584.04}, {"industry": "Not Employed", "total": 2436.6}, {"industry": "Healthcare", "total": 1950.0}, {"industry": "Finance & Insurance", "total": 1575.0}, {"industry": "Government & Public Service", "total": 900.0}, {"industry": "Technology / Engineering", "total": 750.0}, {"industry": "Retail & Hospitality", "total": 620.0}, {"industry": "Construction", "total": 550.0}, {"industry": "Agriculture", "total": 526.57}]}