{"acct_num": "55287", "by_industry": [{"industry": "Political / Lobbying", "total": 1464525.05}, {"industry": "Other", "total": 723612.09}, {"industry": "Finance & Insurance", "total": 581076.56}, {"industry": "Real Estate", "total": 286149.31}, {"industry": "Business & Consulting", "total": 270302.53}, {"industry": "Healthcare", "total": 262196.0}, {"industry": "Legal", "total": 255825.0}, {"industry": "Not Employed", "total": 180586.98}, {"industry": "Construction", "total": 91978.9}, {"industry": "Agriculture", "total": 80600.0}, {"industry": "Retail & Hospitality", "total": 79875.0}, {"industry": "Retired", "total": 72099.83}, {"industry": "Technology / Engineering", "total": 47200.0}, {"industry": "Education", "total": 9100.0}, {"industry": "Government & Public Service", "total": 3700.0}]}