{"acct_num": "60105", "by_industry": [{"industry": "Healthcare", "total": 190794.2}, {"industry": "Political / Lobbying", "total": 58650.0}, {"industry": "Other", "total": 26619.99}, {"industry": "Retired", "total": 19247.31}, {"industry": "Business & Consulting", "total": 18167.0}, {"industry": "Not Employed", "total": 15051.0}, {"industry": "Legal", "total": 7200.0}, {"industry": "Finance & Insurance", "total": 4400.0}, {"industry": "Retail & Hospitality", "total": 4250.0}, {"industry": "Real Estate", "total": 4050.0}, {"industry": "Technology / Engineering", "total": 3500.0}, {"industry": "Agriculture", "total": 1150.0}, {"industry": "Construction", "total": 1000.0}, {"industry": "Education", "total": 400.0}]}