{"acct_num": "60179", "by_industry": [{"industry": "Political / Lobbying", "total": 82582.57}, {"industry": "Other", "total": 76131.28}, {"industry": "Business & Consulting", "total": 38082.44}, {"industry": "Healthcare", "total": 27900.0}, {"industry": "Real Estate", "total": 22050.0}, {"industry": "Finance & Insurance", "total": 20225.0}, {"industry": "Legal", "total": 15590.38}, {"industry": "Construction", "total": 15250.0}, {"industry": "Agriculture", "total": 15000.0}, {"industry": "Not Employed", "total": 13028.0}, {"industry": "Retired", "total": 5100.0}, {"industry": "Retail & Hospitality", "total": 5025.0}, {"industry": "Education", "total": 4750.0}, {"industry": "Technology / Engineering", "total": 4000.0}, {"industry": "Government & Public Service", "total": 200.0}]}