{"acct_num": "60896", "by_industry": [{"industry": "Political / Lobbying", "total": 13694.25}, {"industry": "Retired", "total": 13250.0}, {"industry": "Other", "total": 12143.0}, {"industry": "Healthcare", "total": 10325.0}, {"industry": "Business & Consulting", "total": 7050.0}, {"industry": "Finance & Insurance", "total": 3150.0}, {"industry": "Not Employed", "total": 2070.0}, {"industry": "Legal", "total": 1700.0}, {"industry": "Construction", "total": 1000.0}, {"industry": "Real Estate", "total": 900.0}, {"industry": "Government & Public Service", "total": 500.0}, {"industry": "Education", "total": 200.0}, {"industry": "Agriculture", "total": 100.0}, {"industry": "Technology / Engineering", "total": 50.0}]}