{"acct_num": "64259", "by_industry": [{"industry": "Other", "total": 29750.0}, {"industry": "Political / Lobbying", "total": 14000.0}, {"industry": "Finance & Insurance", "total": 6000.0}, {"industry": "Retail & Hospitality", "total": 3000.0}, {"industry": "Legal", "total": 2144.15}, {"industry": "Real Estate", "total": 2000.0}, {"industry": "Business & Consulting", "total": 1500.0}, {"industry": "Healthcare", "total": 1500.0}, {"industry": "Not Employed", "total": 1000.0}, {"industry": "Government & Public Service", "total": 750.0}, {"industry": "Agriculture", "total": 500.0}, {"industry": "Technology / Engineering", "total": 500.0}]}