{"acct_num": "64516", "by_industry": [{"industry": "Not Employed", "total": 28925.0}, {"industry": "Other", "total": 23252.9}, {"industry": "Political / Lobbying", "total": 13350.0}, {"industry": "Retired", "total": 9375.0}, {"industry": "Business & Consulting", "total": 8951.5}, {"industry": "Legal", "total": 7833.12}, {"industry": "Agriculture", "total": 4000.0}, {"industry": "Healthcare", "total": 3100.0}, {"industry": "Real Estate", "total": 3000.0}, {"industry": "Retail & Hospitality", "total": 3000.0}, {"industry": "Government & Public Service", "total": 1150.0}, {"industry": "Construction", "total": 1000.0}, {"industry": "Education", "total": 500.0}, {"industry": "Finance & Insurance", "total": 475.0}, {"industry": "Technology / Engineering", "total": 100.0}]}