{"acct_num": "64790", "by_industry": [{"industry": "Healthcare", "total": 45368.66}, {"industry": "Not Employed", "total": 7083.0}, {"industry": "Technology / Engineering", "total": 6750.0}, {"industry": "Other", "total": 3953.94}, {"industry": "Real Estate", "total": 3626.0}, {"industry": "Finance & Insurance", "total": 2500.0}, {"industry": "Retail & Hospitality", "total": 2252.0}, {"industry": "Political / Lobbying", "total": 2150.0}, {"industry": "Retired", "total": 2000.0}, {"industry": "Legal", "total": 1652.0}, {"industry": "Education", "total": 1050.0}, {"industry": "Business & Consulting", "total": 750.0}, {"industry": "Government & Public Service", "total": 310.0}]}