{"acct_num": "64829", "by_industry": [{"industry": "Other", "total": 12972.46}, {"industry": "Business & Consulting", "total": 1475.0}, {"industry": "Healthcare", "total": 1350.0}, {"industry": "Education", "total": 1150.0}, {"industry": "Retail & Hospitality", "total": 550.0}, {"industry": "Government & Public Service", "total": 300.0}, {"industry": "Construction", "total": 296.0}, {"industry": "Technology / Engineering", "total": 275.0}, {"industry": "Finance & Insurance", "total": 100.0}, {"industry": "Retired", "total": 25.0}]}