{"acct_num": "65196", "by_industry": [{"industry": "Legal", "total": 4425.0}, {"industry": "Not Employed", "total": 2830.0}, {"industry": "Retired", "total": 2250.0}, {"industry": "Other", "total": 2150.0}, {"industry": "Healthcare", "total": 700.0}, {"industry": "Business & Consulting", "total": 625.0}, {"industry": "Finance & Insurance", "total": 600.0}, {"industry": "Government & Public Service", "total": 350.0}, {"industry": "Real Estate", "total": 300.0}, {"industry": "Political / Lobbying", "total": 250.0}, {"industry": "Retail & Hospitality", "total": 200.0}, {"industry": "Technology / Engineering", "total": 100.0}]}