{"acct_num": "65289", "by_industry": [{"industry": "Political / Lobbying", "total": 409249.62}, {"industry": "Legal", "total": 202743.8}, {"industry": "Other", "total": 73170.53}, {"industry": "Not Employed", "total": 67845.44}, {"industry": "Retired", "total": 60566.31}, {"industry": "Business & Consulting", "total": 46345.81}, {"industry": "Healthcare", "total": 33755.57}, {"industry": "Finance & Insurance", "total": 29750.0}, {"industry": "Real Estate", "total": 29259.71}, {"industry": "Agriculture", "total": 24599.15}, {"industry": "Education", "total": 16395.85}, {"industry": "Retail & Hospitality", "total": 8392.8}, {"industry": "Construction", "total": 7050.0}, {"industry": "Technology / Engineering", "total": 6875.0}, {"industry": "Government & Public Service", "total": 6465.64}]}