{"acct_num": "69432", "by_industry": [{"industry": "Not Employed", "total": 8369.0}, {"industry": "Political / Lobbying", "total": 7500.0}, {"industry": "Finance & Insurance", "total": 4996.28}, {"industry": "Other", "total": 2500.0}, {"industry": "Retired", "total": 2120.0}, {"industry": "Healthcare", "total": 2060.0}, {"industry": "Retail & Hospitality", "total": 2000.0}, {"industry": "Business & Consulting", "total": 1700.0}, {"industry": "Technology / Engineering", "total": 700.0}, {"industry": "Agriculture", "total": 500.0}, {"industry": "Legal", "total": 350.0}, {"industry": "Real Estate", "total": 100.0}]}