{"acct_num": "69517", "by_industry": [{"industry": "Not Employed", "total": 40964.52}, {"industry": "Political / Lobbying", "total": 35500.0}, {"industry": "Retired", "total": 30450.0}, {"industry": "Other", "total": 22875.0}, {"industry": "Business & Consulting", "total": 15400.0}, {"industry": "Legal", "total": 13700.0}, {"industry": "Healthcare", "total": 8950.0}, {"industry": "Technology / Engineering", "total": 7350.0}, {"industry": "Retail & Hospitality", "total": 6475.0}, {"industry": "Education", "total": 4750.0}, {"industry": "Real Estate", "total": 3900.0}, {"industry": "Finance & Insurance", "total": 2430.0}, {"industry": "Construction", "total": 1750.0}, {"industry": "Government & Public Service", "total": 750.0}]}