{"acct_num": "69782", "by_industry": [{"industry": "Political / Lobbying", "total": 516179.34}, {"industry": "Agriculture", "total": 325798.0}, {"industry": "Other", "total": 183658.51}, {"industry": "Business & Consulting", "total": 168892.96}, {"industry": "Real Estate", "total": 165393.44}, {"industry": "Legal", "total": 83858.7}, {"industry": "Retail & Hospitality", "total": 80131.95}, {"industry": "Construction", "total": 79210.95}, {"industry": "Finance & Insurance", "total": 68388.76}, {"industry": "Technology / Engineering", "total": 57150.0}, {"industry": "Healthcare", "total": 47003.11}, {"industry": "Retired", "total": 40292.1}, {"industry": "Not Employed", "total": 35676.0}, {"industry": "Government & Public Service", "total": 5450.0}, {"industry": "Education", "total": 1260.0}]}