{"acct_num": "69912", "by_industry": [{"industry": "Not Employed", "total": 13612.97}, {"industry": "Education", "total": 8267.39}, {"industry": "Other", "total": 6762.24}, {"industry": "Retired", "total": 5745.6}, {"industry": "Business & Consulting", "total": 2826.9}, {"industry": "Healthcare", "total": 2245.54}, {"industry": "Political / Lobbying", "total": 1450.0}, {"industry": "Legal", "total": 903.41}, {"industry": "Technology / Engineering", "total": 835.36}, {"industry": "Retail & Hospitality", "total": 750.0}, {"industry": "Real Estate", "total": 395.0}, {"industry": "Construction", "total": 380.18}, {"industry": "Government & Public Service", "total": 326.98}, {"industry": "Finance & Insurance", "total": 81.36}]}