{"acct_num": "69938", "by_industry": [{"industry": "Not Employed", "total": 127231.83}, {"industry": "Political / Lobbying", "total": 122906.46}, {"industry": "Other", "total": 81206.07}, {"industry": "Retired", "total": 59488.16}, {"industry": "Business & Consulting", "total": 50075.49}, {"industry": "Legal", "total": 38695.83}, {"industry": "Healthcare", "total": 18682.4}, {"industry": "Education", "total": 15731.07}, {"industry": "Real Estate", "total": 15578.76}, {"industry": "Technology / Engineering", "total": 15262.73}, {"industry": "Finance & Insurance", "total": 9989.5}, {"industry": "Retail & Hospitality", "total": 4603.5}, {"industry": "Government & Public Service", "total": 3415.25}, {"industry": "Construction", "total": 2620.0}, {"industry": "Agriculture", "total": 250.0}]}