{"acct_num": "70021", "by_industry": [{"industry": "Not Employed", "total": 256924.32}, {"industry": "Real Estate", "total": 175498.54}, {"industry": "Other", "total": 111916.0}, {"industry": "Healthcare", "total": 111325.0}, {"industry": "Business & Consulting", "total": 86783.2}, {"industry": "Legal", "total": 84383.0}, {"industry": "Retail & Hospitality", "total": 66000.0}, {"industry": "Finance & Insurance", "total": 60025.0}, {"industry": "Retired", "total": 59900.0}, {"industry": "Construction", "total": 41800.0}, {"industry": "Political / Lobbying", "total": 28356.15}, {"industry": "Technology / Engineering", "total": 25700.0}, {"industry": "Education", "total": 15250.0}, {"industry": "Agriculture", "total": 9250.0}, {"industry": "Government & Public Service", "total": 5100.0}]}