{"acct_num": "70162", "by_industry": [{"industry": "Other", "total": 493680.0}, {"industry": "Political / Lobbying", "total": 467999.29}, {"industry": "Finance & Insurance", "total": 361492.32}, {"industry": "Legal", "total": 244358.16}, {"industry": "Business & Consulting", "total": 158844.0}, {"industry": "Real Estate", "total": 142834.42}, {"industry": "Healthcare", "total": 133757.0}, {"industry": "Not Employed", "total": 95861.0}, {"industry": "Retired", "total": 84936.0}, {"industry": "Agriculture", "total": 74600.0}, {"industry": "Retail & Hospitality", "total": 62163.52}, {"industry": "Construction", "total": 54614.79}, {"industry": "Technology / Engineering", "total": 27850.0}, {"industry": "Education", "total": 13675.0}, {"industry": "Government & Public Service", "total": 13213.0}]}