{"acct_num": "70170", "by_industry": [{"industry": "Political / Lobbying", "total": 33700.0}, {"industry": "Legal", "total": 26195.1}, {"industry": "Other", "total": 15025.0}, {"industry": "Business & Consulting", "total": 8921.0}, {"industry": "Real Estate", "total": 8500.0}, {"industry": "Healthcare", "total": 7975.0}, {"industry": "Technology / Engineering", "total": 6850.0}, {"industry": "Not Employed", "total": 6050.0}, {"industry": "Finance & Insurance", "total": 5425.0}, {"industry": "Retired", "total": 5325.0}, {"industry": "Retail & Hospitality", "total": 5300.0}, {"industry": "Construction", "total": 5150.0}, {"industry": "Education", "total": 3325.0}, {"industry": "Government & Public Service", "total": 1250.0}, {"industry": "Agriculture", "total": 400.0}]}