{"acct_num": "71854", "by_industry": [{"industry": "Political / Lobbying", "total": 380075.93}, {"industry": "Not Employed", "total": 170676.11}, {"industry": "Legal", "total": 163987.9}, {"industry": "Government & Public Service", "total": 161013.35}, {"industry": "Business & Consulting", "total": 109285.73}, {"industry": "Other", "total": 88577.85}, {"industry": "Real Estate", "total": 59446.33}, {"industry": "Retired", "total": 42177.99}, {"industry": "Finance & Insurance", "total": 28930.88}, {"industry": "Healthcare", "total": 26566.78}, {"industry": "Retail & Hospitality", "total": 24791.39}, {"industry": "Agriculture", "total": 19395.0}, {"industry": "Construction", "total": 18676.18}, {"industry": "Education", "total": 5942.95}, {"industry": "Technology / Engineering", "total": 5674.25}]}