{"acct_num": "73959", "by_industry": [{"industry": "Political / Lobbying", "total": 93129.63}, {"industry": "Other", "total": 53575.0}, {"industry": "Legal", "total": 32605.0}, {"industry": "Business & Consulting", "total": 23900.0}, {"industry": "Healthcare", "total": 23150.0}, {"industry": "Agriculture", "total": 22350.0}, {"industry": "Real Estate", "total": 14100.0}, {"industry": "Construction", "total": 12900.0}, {"industry": "Government & Public Service", "total": 10300.0}, {"industry": "Retired", "total": 8600.0}, {"industry": "Not Employed", "total": 8450.0}, {"industry": "Retail & Hospitality", "total": 8250.0}, {"industry": "Technology / Engineering", "total": 8100.0}, {"industry": "Finance & Insurance", "total": 6850.0}, {"industry": "Education", "total": 1500.0}]}