{"acct_num": "74178", "by_industry": [{"industry": "Other", "total": 8817.09}, {"industry": "Education", "total": 6870.03}, {"industry": "Political / Lobbying", "total": 5500.0}, {"industry": "Business & Consulting", "total": 2722.6}, {"industry": "Retired", "total": 1896.75}, {"industry": "Healthcare", "total": 1584.15}, {"industry": "Real Estate", "total": 1400.18}, {"industry": "Not Employed", "total": 1190.04}, {"industry": "Finance & Insurance", "total": 810.0}, {"industry": "Legal", "total": 600.0}, {"industry": "Retail & Hospitality", "total": 315.0}, {"industry": "Construction", "total": 250.0}, {"industry": "Government & Public Service", "total": 90.0}]}