{"acct_num": "74590", "by_industry": [{"industry": "Legal", "total": 20241.73}, {"industry": "Other", "total": 15536.63}, {"industry": "Not Employed", "total": 10848.14}, {"industry": "Business & Consulting", "total": 7700.24}, {"industry": "Retired", "total": 4245.2}, {"industry": "Finance & Insurance", "total": 4245.0}, {"industry": "Government & Public Service", "total": 3025.0}, {"industry": "Education", "total": 1125.0}, {"industry": "Healthcare", "total": 825.0}, {"industry": "Retail & Hospitality", "total": 718.15}, {"industry": "Real Estate", "total": 550.0}, {"industry": "Construction", "total": 385.0}, {"industry": "Technology / Engineering", "total": 50.0}]}