{"acct_num": "75558", "by_industry": [{"industry": "Political / Lobbying", "total": 42855.0}, {"industry": "Other", "total": 25906.98}, {"industry": "Legal", "total": 18496.0}, {"industry": "Business & Consulting", "total": 15320.62}, {"industry": "Not Employed", "total": 10538.91}, {"industry": "Real Estate", "total": 6025.0}, {"industry": "Retail & Hospitality", "total": 4000.0}, {"industry": "Government & Public Service", "total": 2950.0}, {"industry": "Healthcare", "total": 2850.0}, {"industry": "Agriculture", "total": 2500.0}, {"industry": "Retired", "total": 2495.4}, {"industry": "Technology / Engineering", "total": 2126.08}, {"industry": "Construction", "total": 2100.0}, {"industry": "Education", "total": 1135.0}, {"industry": "Finance & Insurance", "total": 670.0}]}