{"acct_num": "79194", "by_industry": [{"industry": "Political / Lobbying", "total": 230391.38}, {"industry": "Other", "total": 116884.14}, {"industry": "Real Estate", "total": 66450.0}, {"industry": "Business & Consulting", "total": 59625.0}, {"industry": "Legal", "total": 41776.0}, {"industry": "Construction", "total": 28450.0}, {"industry": "Healthcare", "total": 25860.6}, {"industry": "Retired", "total": 25248.4}, {"industry": "Finance & Insurance", "total": 21800.0}, {"industry": "Technology / Engineering", "total": 15600.0}, {"industry": "Not Employed", "total": 13462.2}, {"industry": "Education", "total": 12200.0}, {"industry": "Retail & Hospitality", "total": 9750.0}, {"industry": "Agriculture", "total": 2000.0}, {"industry": "Government & Public Service", "total": 1100.0}]}