{"acct_num": "79387", "by_industry": [{"industry": "Government & Public Service", "total": 4200.0}, {"industry": "Legal", "total": 2186.65}, {"industry": "Retired", "total": 1845.21}, {"industry": "Real Estate", "total": 350.0}, {"industry": "Education", "total": 263.74}, {"industry": "Other", "total": 225.0}, {"industry": "Construction", "total": 200.0}, {"industry": "Healthcare", "total": 125.0}, {"industry": "Not Employed", "total": 100.0}, {"industry": "Business & Consulting", "total": 50.0}]}