{"acct_num": "79464", "by_industry": [{"industry": "Legal", "total": 61614.27}, {"industry": "Business & Consulting", "total": 7222.0}, {"industry": "Other", "total": 5160.0}, {"industry": "Healthcare", "total": 4240.0}, {"industry": "Construction", "total": 3100.0}, {"industry": "Political / Lobbying", "total": 2500.0}, {"industry": "Real Estate", "total": 2425.55}, {"industry": "Retired", "total": 2000.0}, {"industry": "Not Employed", "total": 1920.0}, {"industry": "Education", "total": 1400.0}, {"industry": "Government & Public Service", "total": 1170.0}, {"industry": "Finance & Insurance", "total": 500.0}, {"industry": "Retail & Hospitality", "total": 50.0}]}