{"acct_num": "79885", "by_industry": [{"industry": "Other", "total": 11020.0}, {"industry": "Retired", "total": 5058.98}, {"industry": "Business & Consulting", "total": 3920.0}, {"industry": "Not Employed", "total": 1520.0}, {"industry": "Legal", "total": 1500.0}, {"industry": "Education", "total": 1400.0}, {"industry": "Construction", "total": 1000.0}, {"industry": "Technology / Engineering", "total": 750.0}, {"industry": "Healthcare", "total": 450.0}, {"industry": "Real Estate", "total": 150.0}]}