{"acct_num": "80015", "by_industry": [{"industry": "Political / Lobbying", "total": 109126.72}, {"industry": "Business & Consulting", "total": 26708.0}, {"industry": "Finance & Insurance", "total": 22720.0}, {"industry": "Real Estate", "total": 21650.0}, {"industry": "Legal", "total": 12490.0}, {"industry": "Healthcare", "total": 9280.0}, {"industry": "Other", "total": 9195.0}, {"industry": "Agriculture", "total": 7200.0}, {"industry": "Not Employed", "total": 6430.0}, {"industry": "Retired", "total": 6000.0}, {"industry": "Construction", "total": 4600.0}, {"industry": "Government & Public Service", "total": 3000.0}, {"industry": "Retail & Hospitality", "total": 2500.0}, {"industry": "Technology / Engineering", "total": 2300.0}, {"industry": "Education", "total": 325.0}]}