{"acct_num": "80188", "by_industry": [{"industry": "Other", "total": 18141.51}, {"industry": "Not Employed", "total": 4238.99}, {"industry": "Retired", "total": 2995.0}, {"industry": "Real Estate", "total": 1950.0}, {"industry": "Legal", "total": 1650.0}, {"industry": "Business & Consulting", "total": 650.0}, {"industry": "Education", "total": 500.0}, {"industry": "Construction", "total": 250.0}, {"industry": "Finance & Insurance", "total": 250.0}, {"industry": "Healthcare", "total": 250.0}, {"industry": "Technology / Engineering", "total": 100.0}, {"industry": "Government & Public Service", "total": 50.0}]}