{"acct_num": "80227", "by_industry": [{"industry": "Legal", "total": 102365.89}, {"industry": "Business & Consulting", "total": 9457.5}, {"industry": "Other", "total": 7790.0}, {"industry": "Healthcare", "total": 6150.0}, {"industry": "Real Estate", "total": 3299.0}, {"industry": "Not Employed", "total": 3115.45}, {"industry": "Education", "total": 1625.0}, {"industry": "Retired", "total": 1560.0}, {"industry": "Technology / Engineering", "total": 1505.0}, {"industry": "Construction", "total": 705.0}, {"industry": "Finance & Insurance", "total": 250.0}, {"industry": "Political / Lobbying", "total": 250.0}, {"industry": "Government & Public Service", "total": 50.0}]}