{"acct_num": "83480", "by_industry": [{"industry": "Political / Lobbying", "total": 47725.0}, {"industry": "Other", "total": 29300.0}, {"industry": "Business & Consulting", "total": 12750.0}, {"industry": "Legal", "total": 7250.0}, {"industry": "Healthcare", "total": 6500.0}, {"industry": "Real Estate", "total": 4000.0}, {"industry": "Finance & Insurance", "total": 3550.0}, {"industry": "Retail & Hospitality", "total": 2000.0}, {"industry": "Education", "total": 1400.0}, {"industry": "Retired", "total": 1300.0}, {"industry": "Not Employed", "total": 1100.0}, {"industry": "Agriculture", "total": 1000.0}, {"industry": "Technology / Engineering", "total": 575.0}]}