{"acct_num": "83642", "by_industry": [{"industry": "Not Employed", "total": 93407.46}, {"industry": "Retired", "total": 66121.42}, {"industry": "Other", "total": 55340.45}, {"industry": "Business & Consulting", "total": 43213.53}, {"industry": "Legal", "total": 23667.11}, {"industry": "Political / Lobbying", "total": 22947.8}, {"industry": "Healthcare", "total": 14878.0}, {"industry": "Education", "total": 13942.0}, {"industry": "Real Estate", "total": 12966.81}, {"industry": "Finance & Insurance", "total": 9100.0}, {"industry": "Technology / Engineering", "total": 8022.64}, {"industry": "Construction", "total": 2034.75}, {"industry": "Government & Public Service", "total": 1200.0}]}