{"acct_num": "83704", "by_industry": [{"industry": "Political / Lobbying", "total": 177223.28}, {"industry": "Other", "total": 23999.13}, {"industry": "Business & Consulting", "total": 22950.0}, {"industry": "Legal", "total": 15050.0}, {"industry": "Construction", "total": 12850.0}, {"industry": "Finance & Insurance", "total": 10650.0}, {"industry": "Agriculture", "total": 10200.0}, {"industry": "Healthcare", "total": 9500.0}, {"industry": "Technology / Engineering", "total": 7600.0}, {"industry": "Retail & Hospitality", "total": 6700.0}, {"industry": "Real Estate", "total": 6150.0}, {"industry": "Education", "total": 3000.0}, {"industry": "Government & Public Service", "total": 2450.0}, {"industry": "Not Employed", "total": 1625.0}, {"industry": "Retired", "total": 1050.0}]}