{"acct_num": "83829", "by_industry": [{"industry": "Real Estate", "total": 133250.67}, {"industry": "Political / Lobbying", "total": 63000.0}, {"industry": "Retired", "total": 52829.09}, {"industry": "Other", "total": 16816.1}, {"industry": "Business & Consulting", "total": 16179.1}, {"industry": "Not Employed", "total": 8099.1}, {"industry": "Retail & Hospitality", "total": 6000.0}, {"industry": "Finance & Insurance", "total": 5500.0}, {"industry": "Construction", "total": 5316.02}, {"industry": "Healthcare", "total": 5100.0}, {"industry": "Technology / Engineering", "total": 3664.35}, {"industry": "Legal", "total": 2654.1}, {"industry": "Agriculture", "total": 2500.0}, {"industry": "Education", "total": 800.0}, {"industry": "Government & Public Service", "total": 750.0}]}