{"acct_num": "83997", "by_industry": [{"industry": "Legal", "total": 84894.85}, {"industry": "Not Employed", "total": 1952.84}, {"industry": "Retired", "total": 1917.31}, {"industry": "Other", "total": 1802.75}, {"industry": "Education", "total": 1150.0}, {"industry": "Business & Consulting", "total": 885.76}, {"industry": "Real Estate", "total": 461.38}, {"industry": "Technology / Engineering", "total": 100.06}, {"industry": "Healthcare", "total": 79.09}, {"industry": "Construction", "total": 16.05}]}