{"acct_num": "84088", "by_industry": [{"industry": "Other", "total": 6820.93}, {"industry": "Not Employed", "total": 6733.65}, {"industry": "Technology / Engineering", "total": 5620.97}, {"industry": "Business & Consulting", "total": 2967.28}, {"industry": "Healthcare", "total": 1863.57}, {"industry": "Retired", "total": 1821.0}, {"industry": "Political / Lobbying", "total": 1350.0}, {"industry": "Legal", "total": 1251.0}, {"industry": "Construction", "total": 500.0}, {"industry": "Education", "total": 302.88}, {"industry": "Real Estate", "total": 250.0}, {"industry": "Finance & Insurance", "total": 58.16}, {"industry": "Government & Public Service", "total": 25.0}, {"industry": "Retail & Hospitality", "total": 17.86}]}