{"acct_num": "86567", "by_industry": [{"industry": "Not Employed", "total": 7450.71}, {"industry": "Political / Lobbying", "total": 5525.0}, {"industry": "Other", "total": 2050.62}, {"industry": "Business & Consulting", "total": 2038.12}, {"industry": "Education", "total": 1640.0}, {"industry": "Retired", "total": 1512.27}, {"industry": "Healthcare", "total": 825.26}, {"industry": "Technology / Engineering", "total": 744.75}, {"industry": "Legal", "total": 482.15}, {"industry": "Real Estate", "total": 180.0}, {"industry": "Finance & Insurance", "total": 160.0}, {"industry": "Government & Public Service", "total": 92.0}, {"industry": "Construction", "total": 29.24}]}