{"acct_num": "88827", "by_industry": [{"industry": "Political / Lobbying", "total": 44450.0}, {"industry": "Other", "total": 17485.88}, {"industry": "Real Estate", "total": 4010.0}, {"industry": "Business & Consulting", "total": 3700.0}, {"industry": "Finance & Insurance", "total": 3450.0}, {"industry": "Retired", "total": 3041.0}, {"industry": "Healthcare", "total": 2100.0}, {"industry": "Legal", "total": 1900.0}, {"industry": "Agriculture", "total": 1000.0}, {"industry": "Education", "total": 700.0}, {"industry": "Government & Public Service", "total": 300.0}, {"industry": "Not Employed", "total": 200.0}, {"industry": "Technology / Engineering", "total": 100.0}, {"industry": "Construction", "total": 25.0}]}